mypackage/SAFW.py
mypackage/__init__.py
mypackage/logBarrier.py
safeOptimization-0.0.4.dist-info/LICENSE
safeOptimization-0.0.4.dist-info/METADATA
safeOptimization-0.0.4.dist-info/WHEEL
safeOptimization-0.0.4.dist-info/top_level.txt
safeOptimization-0.0.4.dist-info/RECORD
