Metadata-Version: 2.1
Name: safeOptimization
Version: 0.0.4
Summary: A package for safe optimization algorithms.
Home-page: https://github.com/m5a0r7/safeOpt
Author: Mohammad Amin Roohi
Author-email: m5a0r7@gmail.com
Classifier: Programming Language :: Python :: 3
Classifier: License :: OSI Approved :: MIT License
Classifier: Operating System :: OS Independent
Requires-Python: >=3.6
License-File: LICENSE
